speciesfinder-4.0.1.dist-info/METADATA
speciesfinder-4.0.1.dist-info/WHEEL
speciesfinder-4.0.1.dist-info/entry_points.txt
speciesfinder/__init__.py
speciesfinder/__main__.py
speciesfinder/speciesfinder_args_functions.py
speciesfinder/speciesfinder_kma_and_taxonomy.py
speciesfinder/speciesfinder_main.py
speciesfinder/speciesfinder_pre_functions.py
speciesfinder/speciesfinder_run.py
speciesfinder-4.0.1.dist-info/RECORD
