Metadata-Version: 2.1
Name: SpeciesFinder
Version: 4.0.1
Summary: The SpeciesFinder tool identifies species from raw sequencing reads (FASTQ) or assembled genomes (FASTA) by comparing them against a database generated using the KMA program. It reports the best matching species, along with additional taxonomic information if that option is selected.
Author-Email: Center for Genomic Epidemiology <food-cgehelp@dtu.dk>
License: Apache-2.0
Requires-Python: >=3.10
